{
  "Adalar": [
    "Burgazada Mah.",
    "Heybeliada Mah.",
    "Kınalıada Mah.",
    "Maden Mah.",
    "Nizam Mah."
  ],
  "Arnavutköy": [
    "Adnan Menderes Mah.",
    "Anadolu Mah.",
    "Arnavutköy Merkez Mah.",
    "Baklalı Mah.",
    "Balaban Mah.",
    "Bolluca Mah.",
    "Boğazköy İstiklal Mah.",
    "Boğazköy Merkez Mah.",
    "Durusu Mah.",
    "Dursunköy Mah.",
    "Hacımaşlı Mah.",
    "Hadımköy Mah.",
    "Haraççı Mah.",
    "Hastane Mah.",
    "İmrahor Mah.",
    "İslambey Mah.",
    "Karaburun Mah.",
    "Mareşal Fevzi Çakmak Mah.",
    "Mehmet Akif Ersoy Mah.",
    "Mustafa Kemal Paşa Mah.",
    "Nenehatun Mah.",
    "Sazlıbosna Mah.",
    "Taşoluk Mah.",
    "Yassıören Mah.",
    "Yeniköy Mah.",
    "Yeşilbayır Mah.",
    "Yıldırım Beyazıt Mah.",
    "Yunus Emre Mah."
  ],
  "Ataşehir": [
    "Aşık Veysel Mah.",
    "Atatürk Mah.",
    "Barbaros Mah.",
    "Esatpaşa Mah.",
    "Ferhatpaşa Mah.",
    "Fetih Mah.",
    "İçerenköy Mah.",
    "İnönü Mah.",
    "Kayışdağı Mah.",
    "Küçükbakkalköy Mah.",
    "Mevlana Mah.",
    "Mimar Sinan Mah.",
    "Mustafa Kemal Mah.",
    "Örnek Mah.",
    "Yeni Çamlıca Mah.",
    "Yenişehir Mah.",
    "Yenisahra Mah."
  ],
  "Avcılar": [
    "Ambarlı Mah.",
    "Cihangir Mah.",
    "Denizköşkler Mah.",
    "Firuzköy Mah.",
    "Gümüşpala Mah.",
    "Merkez Mah.",
    "Mustafa Kemal Paşa Mah.",
    "Tahtakale Mah.",
    "Üniversite Mah.",
    "Yeşilkent Mah."
  ],
  "Bağcılar": [
    "100. Yıl Mah.",
    "Bağlar Mah.",
    "Barbaros Mah.",
    "Çınar Mah.",
    "Demirkapı Mah.",
    "Fatih Mah.",
    "Fevzi Çakmak Mah.",
    "Göztepe Mah.",
    "Güneşli Mah.",
    "Hürriyet Mah.",
    "İnönü Mah.",
    "Kazım Karabekir Mah.",
    "Kemalpaşa Mah.",
    "Kirazlı Mah.",
    "Mahmutbey Mah.",
    "Merkez Mah.",
    "Sancaktepe Mah.",
    "Yavuz Selim Mah.",
    "Yenigün Mah.",
    "Yıldıztepe Mah.",
    "Yunus Emre Mah.",
    "Zafer Mah."
  ],
  "Bahçelievler": [
    "Bahçelievler Mah.",
    "Cumhuriyet Mah.",
    "Çobançeşme Mah.",
    "Fevzi Çakmak Mah.",
    "Hürriyet Mah.",
    "Kocasinan Merkez Mah.",
    "Siyavuşpaşa Mah.",
    "Soğanlı Mah.",
    "Şirinevler Mah.",
    "Yenibosna Merkez Mah.",
    "Zafer Mah."
  ],
  "Bakırköy": [
    "Ataköy 1. Kısım Mah.",
    "Ataköy 2-5-6. Kısım Mah.",
    "Ataköy 3-4-11. Kısım Mah.",
    "Ataköy 7-8-9-10. Kısım Mah.",
    "Basınköy Mah.",
    "Cevizlik Mah.",
    "Kartaltepe Mah.",
    "Osmaniye Mah.",
    "Sakızağacı Mah.",
    "Şenlikköy Mah.",
    "Yenimahalle Mah.",
    "Yeşilköy Mah.",
    "Yeşilyurt Mah.",
    "Zeytinlik Mah.",
    "Zuhuratbaba Mah."
  ],
  "Başakşehir": [
    "Altınşehir Mah.",
    "Bahçeşehir 1. Kısım Mah.",
    "Bahçeşehir 2. Kısım Mah.",
    "Başak Mah.",
    "Güvercintepe Mah.",
    "İkitelli OSB Mah.",
    "Kayabaşı Mah.",
    "Şahintepe Mah.",
    "Ziya Gökalp Mah."
  ],
  "Bayrampaşa": [
    "Altıntepsi Mah.",
    "Cevatpaşa Mah.",
    "İsmet Paşa Mah.",
    "Kartaltepe Mah.",
    "Kocatepe Mah.",
    "Muratpaşa Mah.",
    "Orta Mah.",
    "Terazidere Mah.",
    "Vatan Mah.",
    "Yenidoğan Mah.",
    "Yıldırım Mah."
  ],
  "Beşiktaş": [
    "Abbasağa Mah.",
    "Akaretler Mah.",
    "Bebek Mah.",
    "Dikilitaş Mah.",
    "Etiler Mah.",
    "Gayrettepe Mah.",
    "Levent Mah.",
    "Muradiye Mah.",
    "Ortaköy Mah.",
    "Sinanpaşa Mah.",
    "Türkali Mah.",
    "Vişnezade Mah.",
    "Yıldız Mah."
  ],
  "Beykoz": [
    "Akbaba Mah.",
    "Anadolu Feneri Mah.",
    "Çubuklu Mah.",
    "Dereseki Mah.",
    "Göksu Mah.",
    "Kanlıca Mah.",
    "Kavacık Mah.",
    "Mahmutşevketpaşa Mah.",
    "Paşabahçe Mah.",
    "Polonezköy Mah.",
    "Poyrazköy Mah.",
    "Riva Mah.",
    "Soğuksu Mah.",
    "Tokatköy Mah.",
    "Yalıköy Mah."
  ],
  "Beylikdüzü": [
    "Adnan Kahveci Mah.",
    "Barış Mah.",
    "Büyükşehir Mah.",
    "Cumhuriyet Mah.",
    "Dereağzı Mah.",
    "Gürpınar Mah.",
    "Kavaklı Mah.",
    "Marmara Mah.",
    "Sahil Mah.",
    "Yakuplu Mah."
  ],
  "Beyoğlu": [
    "Arap Cami Mah.",
    "Asmalımescit Mah.",
    "Bereketzade Mah.",
    "Camiikebir Mah.",
    "Cihangir Mah.",
    "Emekyemez Mah.",
    "Firuzağa Mah.",
    "Galata Mah.",
    "Hacımimi Mah.",
    "Karaköy Mah.",
    "Kocatepe Mah.",
    "Piyalepaşa Mah.",
    "Şahkulu Mah.",
    "Tomtom Mah."
  ],
  "Büyükçekmece": [
    "19 Mayıs Mah.",
    "Ahmediye Mah.",
    "Alkent 2000 Mah.",
    "Atatürk Mah.",
    "Celaliye Mah.",
    "Cumhuriyet Mah.",
    "Dizdariye Mah.",
    "Ekinoba Mah.",
    "Fatih Mah.",
    "Güzelce Mah.",
    "Hürriyet Mah.",
    "Kamiloba Mah.",
    "Karaağaç Mah.",
    "Mimaroba Mah.",
    "Muratçeşme Mah.",
    "Sinanoba Mah.",
    "Tepecik Mah."
  ],
  "Çatalca": [
    "Akalan Mah.",
    "Aydınlar Mah.",
    "Bahşayiş Mah.",
    "Belgrat Mah.",
    "Celepköy Mah.",
    "Çakıl Mah.",
    "Dağyenice Mah.",
    "Elbasan Mah.",
    "Ferhatpaşa Mah.",
    "Gökçeali Mah.",
    "Hallaçlı Mah.",
    "Hisarbeyli Mah.",
    "İhsaniye Mah.",
    "İnceğiz Mah.",
    "Kabakça Mah.",
    "Kalfa Mah.",
    "Kestanelik Mah.",
    "Kızılcaali Mah.",
    "Muratbey Mah.",
    "Nakkaş Mah.",
    "Oklalı Mah.",
    "Örcünlü Mah.",
    "Subaşı Mah.",
    "Yalıköy Mah.",
    "Yaylacık Mah."
  ],
  "Çekmeköy": [
    "Alemdağ Mah.",
    "Aydınlar Mah.",
    "Cumhuriyet Mah.",
    "Çamlık Mah.",
    "Ekşioğlu Mah.",
    "Hamidiye Mah.",
    "Kirazlıdere Mah.",
    "Koçullu Mah.",
    "Mehmet Akif Mah.",
    "Merkez Mah.",
    "Mimar Sinan Mah.",
    "Nişantepe Mah.",
    "Reşadiye Mah.",
    "Sırapınar Mah.",
    "Taşdelen Mah."
  ],
  "Esenler": [
    "Birlik Mah.",
    "Çiftehavuzlar Mah.",
    "Davutpaşa Mah.",
    "Fatih Mah.",
    "Fevzi Çakmak Mah.",
    "Havaalanı Mah.",
    "Kazım Karabekir Mah.",
    "Kemer Mah.",
    "Menderes Mah.",
    "Namık Kemal Mah.",
    "Nine Hatun Mah.",
    "Oruçreis Mah.",
    "Tuna Mah.",
    "Yavuz Selim Mah."
  ],
  "Esenyurt": [
    "Akçaburgaz Mah.",
    "Akevler Mah.",
    "Akşemseddin Mah.",
    "Ardıçlı Mah.",
    "Aşık Veysel Mah.",
    "Atatürk Mah.",
    "Balıkyolu Mah.",
    "Battalgazi Mah.",
    "Cumhuriyet Mah.",
    "Çınar Mah.",
    "Fatih Mah.",
    "Gökevler Mah.",
    "Güzelyurt Mah.",
    "Hürriyet Mah.",
    "İncirtepe Mah.",
    "İnönü Mah.",
    "İstiklal Mah.",
    "Mehterçeşme Mah.",
    "Mevlana Mah.",
    "Namık Kemal Mah.",
    "Necip Fazıl Mah.",
    "Orhan Gazi Mah.",
    "Osmangazi Mah.",
    "Pınar Mah.",
    "Saadetdere Mah.",
    "Selahaddin Eyyubi Mah.",
    "Sultaniye Mah.",
    "Süleymaniye Mah.",
    "Turgut Özal Mah.",
    "Üçevler Mah.",
    "Yenikent Mah."
  ],
  "Eyüpsultan": [
    "Akşemsettin Mah.",
    "Alibeyköy Mah.",
    "Çırçır Mah.",
    "Defterdar Mah.",
    "Düğmeciler Mah.",
    "Emniyettepe Mah.",
    "Esentepe Mah.",
    "Güzeltepe Mah.",
    "İslambey Mah.",
    "Karadolap Mah.",
    "Mithatpaşa Mah.",
    "Nişanca Mah.",
    "Rami Cuma Mah.",
    "Rami Yeni Mah.",
    "Sakarya Mah.",
    "Silahtarağa Mah.",
    "Topçular Mah.",
    "Yeşilpınar Mah."
  ],
  "Fatih": [
    "Aksaray Mah.",
    "Akşemsettin Mah.",
    "Alemdar Mah.",
    "Ali Kuşçu Mah.",
    "Balabanağa Mah.",
    "Balat Mah.",
    "Beyazıt Mah.",
    "Binbirdirek Mah.",
    "Cankurtaran Mah.",
    "Cerrahpaşa Mah.",
    "Demirtaş Mah.",
    "Derviş Ali Mah.",
    "Emin Sinan Mah.",
    "Hacı Kadın Mah.",
    "Haseki Sultan Mah.",
    "Hırka-i Şerif Mah.",
    "Hobyar Mah.",
    "İskenderpaşa Mah.",
    "Kalenderhane Mah.",
    "Karagümrük Mah.",
    "Katip Kasım Mah.",
    "Kemalpaşa Mah.",
    "Koca Mustafapaşa Mah.",
    "Mimar Hayrettin Mah.",
    "Mimar Kemalettin Mah.",
    "Muhsine Hatun Mah.",
    "Nişanca Mah.",
    "Rüstempaşa Mah.",
    "Saraç İshak Mah.",
    "Seyyid Ömer Mah.",
    "Silivrikapı Mah.",
    "Süleymaniye Mah.",
    "Sururi Mah.",
    "Şehremini Mah.",
    "Tahtakale Mah.",
    "Taya Hatun Mah.",
    "Yavuz Sinan Mah.",
    "Yedikule Mah."
  ],
  "Gaziosmanpaşa": [
    "Bağlarbaşı Mah.",
    "Barbaros Hayrettin Paşa Mah.",
    "Fevzi Çakmak Mah.",
    "Hürriyet Mah.",
    "Karadeniz Mah.",
    "Karayolları Mah.",
    "Kazım Karabekir Mah.",
    "Merkez Mah.",
    "Mevlana Mah.",
    "Pazariçi Mah.",
    "Sarıgöl Mah.",
    "Şemsipaşa Mah.",
    "Yeni Mah."
  ],
  "Güngören": [
    "Abdurrahman Nafiz Gürman Mah.",
    "Akıncılar Mah.",
    "Gençosman Mah.",
    "Güneştepe Mah.",
    "Güven Mah.",
    "Haznedar Mah.",
    "Mareşal Çakmak Mah.",
    "Mehmet Nesih Özmen Mah.",
    "Sanayi Mah.",
    "Tozkoparan Mah."
  ],
  "Kadıköy": [
    "Acıbadem Mah.",
    "Bostancı Mah.",
    "Caddebostan Mah.",
    "Caferağa Mah.",
    "Dumlupınar Mah.",
    "Erenköy Mah.",
    "Fenerbahçe Mah.",
    "Feneryolu Mah.",
    "Fikirtepe Mah.",
    "Göztepe Mah.",
    "Hasanpaşa Mah.",
    "Koşuyolu Mah.",
    "Merdivenköy Mah.",
    "Moda Mah.",
    "Osmanağa Mah.",
    "Rasimpaşa Mah.",
    "Sahrayıcedid Mah.",
    "Suadiye Mah.",
    "Zühtüpaşa Mah."
  ],
  "Kartal": [
    "Atalar Mah.",
    "Cevizli Mah.",
    "Cumhuriyet Mah.",
    "Esentepe Mah.",
    "Gümüşpınar Mah.",
    "Hürriyet Mah.",
    "Karlıktepe Mah.",
    "Kordonboyu Mah.",
    "Orhantepe Mah.",
    "Petrol İş Mah.",
    "Soğanlık Yeni Mah.",
    "Topselvi Mah.",
    "Uğur Mumcu Mah.",
    "Yakacık Çarşı Mah.",
    "Yakacık Yeni Mah.",
    "Yalı Mah.",
    "Yukarı Mah."
  ],
  "Kağıthane": [
    "Çağlayan Mah.",
    "Çeliktepe Mah.",
    "Emniyet Evleri Mah.",
    "Gültepe Mah.",
    "Gürsel Mah.",
    "Hamidiye Mah.",
    "Harmantepe Mah.",
    "Hürriyet Mah.",
    "Mehmet Akif Ersoy Mah.",
    "Merkez Mah.",
    "Nurtepe Mah.",
    "Ortabayır Mah.",
    "Seyrantepe Mah.",
    "Talatpaşa Mah.",
    "Yahya Kemal Mah."
  ],
  "Küçükçekmece": [
    "Atakent Mah.",
    "Atatürk Mah.",
    "Beşyol Mah.",
    "Cennet Mah.",
    "Cumhuriyet Mah.",
    "Fatih Mah.",
    "Fevzi Çakmak Mah.",
    "Gültepe Mah.",
    "Halkalı Merkez Mah.",
    "İnönü Mah.",
    "Kanarya Mah.",
    "Kartaltepe Mah.",
    "Kemalpaşa Mah.",
    "Mehmet Akif Mah.",
    "Söğütlüçeşme Mah.",
    "Sultanmurat Mah.",
    "Tevfikbey Mah.",
    "Yarımburgaz Mah.",
    "Yenimahalle Mah.",
    "Yeşilova Mah."
  ],
  "Maltepe": [
    "Altayçeşme Mah.",
    "Altıntepe Mah.",
    "Aydınevler Mah.",
    "Bağlarbaşı Mah.",
    "Başıbüyük Mah.",
    "Büyükbakkalköy Mah.",
    "Cevizli Mah.",
    "Çınar Mah.",
    "Esenkent Mah.",
    "Feyzullah Mah.",
    "Gülsuyu Mah.",
    "Gülensu Mah.",
    "İdealtepe Mah.",
    "Küçükyalı Mah.",
    "Yalı Mah.",
    "Zümrütevler Mah."
  ],
  "Pendik": [
    "Ahmet Yesevi Mah.",
    "Bahçelievler Mah.",
    "Batı Mah.",
    "Çamçeşme Mah.",
    "Çınardere Mah.",
    "Doğu Mah.",
    "Dumlupınar Mah.",
    "Esenler Mah.",
    "Fatih Mah.",
    "Fevzi Çakmak Mah.",
    "Güllübağlar Mah.",
    "Harmandere Mah.",
    "Kavakpınar Mah.",
    "Kaynarca Mah.",
    "Kurtköy Mah.",
    "Orhangazi Mah.",
    "Orta Mah.",
    "Ramazanoğlu Mah.",
    "Sanayi Mah.",
    "Sapanbağları Mah.",
    "Şeyhli Mah.",
    "Velibaba Mah.",
    "Yeni Mah.",
    "Yayalar Mah.",
    "Yeşilbağlar Mah."
  ],
  "Sancaktepe": [
    "Abdurrahmangazi Mah.",
    "Akpınar Mah.",
    "Atatürk Mah.",
    "Emek Mah.",
    "Eyüp Sultan Mah.",
    "Fatih Mah.",
    "Hilal Mah.",
    "İnönü Mah.",
    "Kemal Türkler Mah.",
    "Meclis Mah.",
    "Merve Mah.",
    "Osmangazi Mah.",
    "Paşaköy Mah.",
    "Safa Mah.",
    "Sarıgazi Mah.",
    "Veysel Karani Mah.",
    "Yenidoğan Mah."
  ],
  "Sarıyer": [
    "Ayazağa Mah.",
    "Bahçeköy Kemer Mah.",
    "Bahçeköy Merkez Mah.",
    "Bahçeköy Yeni Mah.",
    "Baltalimanı Mah.",
    "Büyükdere Mah.",
    "Cumhuriyet Mah.",
    "Çamlıtepe Mah.",
    "Darüşşafaka Mah.",
    "Demirciköy Mah.",
    "Emirgan Mah.",
    "Ferahevler Mah.",
    "Garipçe Mah.",
    "Gümüşdere Mah.",
    "Huzur Mah.",
    "İstinye Mah.",
    "Kâzım Karabekir Paşa Mah.",
    "Kireçburnu Mah.",
    "Kocataş Mah.",
    "Maslak Mah.",
    "Pınar Mah.",
    "Poligon Mah.",
    "Reşitpaşa Mah.",
    "Rumelifeneri Mah.",
    "Rumelihisarı Mah.",
    "Tarabya Mah.",
    "Yeniköy Mah.",
    "Zekeriyaköy Mah."
  ],
  "Silivri": [
    "Akören Mah.",
    "Alibey Mah.",
    "Büyükçavuşlu Mah.",
    "Cumhuriyet Mah.",
    "Değirmenköy İsmetpaşa Mah.",
    "Değirmenköy Fevzipaşa Mah.",
    "Fatih Mah.",
    "Gazitepe Mah.",
    "Gümüşyaka Mah.",
    "Kadıköy Mah.",
    "Kavaklı Mah.",
    "Mimar Sinan Mah.",
    "Ortamahalle Mah.",
    "Piri Mehmet Paşa Mah.",
    "Selimpaşa Mah.",
    "Semizkumlar Mah.",
    "Yeni Mah."
  ],
  "Sultanbeyli": [
    "Abdurrahmangazi Mah.",
    "Adil Mah.",
    "Akşemsettin Mah.",
    "Battalgazi Mah.",
    "Fatih Mah.",
    "Hamidiye Mah.",
    "Hasanpaşa Mah.",
    "Mehmet Akif Mah.",
    "Mimar Sinan Mah.",
    "Necip Fazıl Mah.",
    "Orhangazi Mah.",
    "Turgut Reis Mah.",
    "Yavuz Selim Mah."
  ],
  "Sultangazi": [
    "50. Yıl Mah.",
    "75. Yıl Mah.",
    "Cebeci Mah.",
    "Cumhuriyet Mah.",
    "Esentepe Mah.",
    "Gazi Mah.",
    "Habibler Mah.",
    "İsmetpaşa Mah.",
    "Malkoçoğlu Mah.",
    "Sultançiftliği Mah.",
    "Uğur Mumcu Mah.",
    "Yayla Mah.",
    "Yunus Emre Mah."
  ],
  "Şile": [
    "Ağva Merkez Mah.",
    "Ahmetli Mah.",
    "Balibey Mah.",
    "Bucaklı Mah.",
    "Çavuş Mah.",
    "Çengilli Mah.",
    "Doğancılı Mah.",
    "Erenler Mah.",
    "Hacıllı Mah.",
    "İmrenli Mah.",
    "Kalem Mah.",
    "Karabeyli Mah.",
    "Kızılca Mah.",
    "Meşrutiyet Mah.",
    "Ovacık Mah.",
    "Sahilköy Mah.",
    "Sofular Mah.",
    "Yaylalı Mah."
  ],
  "Şişli": [
    "19 Mayıs Mah.",
    "Bozkurt Mah.",
    "Cumhuriyet Mah.",
    "Duatepe Mah.",
    "Ergenekon Mah.",
    "Esentepe Mah.",
    "Feriköy Mah.",
    "Fulya Mah.",
    "Halide Edib Adıvar Mah.",
    "Halil Rıfat Paşa Mah.",
    "Harbiye Mah.",
    "İnönü Mah.",
    "Kaptanpaşa Mah.",
    "Kuştepe Mah.",
    "Mahmut Şevket Paşa Mah.",
    "Mecidiyeköy Mah.",
    "Merkez Mah.",
    "Paşa Mah.",
    "Teşvikiye Mah."
  ],
  "Tuzla": [
    "Akfırat Mah.",
    "Aydınlı Mah.",
    "Aydıntepe Mah.",
    "Cami Mah.",
    "Evliya Çelebi Mah.",
    "Fatih Mah.",
    "İçmeler Mah.",
    "İstasyon Mah.",
    "Mescit Mah.",
    "Mimar Sinan Mah.",
    "Orhanlı Mah.",
    "Postane Mah.",
    "Şifa Mah.",
    "Tepeören Mah.",
    "Yayla Mah."
  ],
  "Ümraniye": [
    "Altınşehir Mah.",
    "Armağanevler Mah.",
    "Atakent Mah.",
    "Aşağı Dudullu Mah.",
    "Çakmak Mah.",
    "Çamlık Mah.",
    "Dudullu OSB Mah.",
    "Elmalıkent Mah.",
    "Esenkent Mah.",
    "Esenşehir Mah.",
    "Fatih Sultan Mehmet Mah.",
    "Hekimbaşı Mah.",
    "Ihlamurkuyu Mah.",
    "İnkılap Mah.",
    "Kazım Karabekir Mah.",
    "Mehmet Akif Mah.",
    "Namık Kemal Mah.",
    "Necip Fazıl Mah.",
    "Parseller Mah.",
    "Site Mah.",
    "Şerifali Mah.",
    "Tatlısu Mah.",
    "Tepeüstü Mah.",
    "Topağacı Mah.",
    "Yamanevler Mah."
  ],
  "Üsküdar": [
    "Acıbadem Mah.",
    "Ahmediye Mah.",
    "Altunizade Mah.",
    "Aziz Mahmud Hüdayi Mah.",
    "Bağlarbaşı Mah.",
    "Beylerbeyi Mah.",
    "Bulgurlu Mah.",
    "Cumhuriyet Mah.",
    "Çengelköy Mah.",
    "Ferah Mah.",
    "Güzeltepe Mah.",
    "İcadiye Mah.",
    "Kandilli Mah.",
    "Kirazlıtepe Mah.",
    "Kısıklı Mah.",
    "Kuleli Mah.",
    "Kuzguncuk Mah.",
    "Küplüce Mah.",
    "Mehmet Akif Ersoy Mah.",
    "Mimar Sinan Mah.",
    "Muratreis Mah.",
    "Salacak Mah.",
    "Selami Ali Mah.",
    "Selimiye Mah.",
    "Sultantepe Mah.",
    "Ünalan Mah.",
    "Valide-i Atik Mah.",
    "Yavuztürk Mah.",
    "Zeynep Kamil Mah."
  ],
  "Zeytinburnu": [
    "Beştelsiz Mah.",
    "Çırpıcı Mah.",
    "Gökalp Mah.",
    "Kazlıçeşme Mah.",
    "Maltepe Mah.",
    "Merkezefendi Mah.",
    "Nuripaşa Mah.",
    "Seyitnizam Mah.",
    "Sümer Mah.",
    "Telsiz Mah.",
    "Veliefendi Mah."
  ]
}